{
  "project_info": {
    "project_number": "415111056854",
    "firebase_url": "https://emrloop-mobile.firebaseio.com",
    "project_id": "emrloop-mobile",
    "storage_bucket": "emrloop-mobile.appspot.com"
  },
  "client": [
    {
      "client_info": {
        "mobilesdk_app_id": "1:415111056854:android:d71257d4621a5a70d76877",
        "android_client_info": {
          "package_name": "com.syftet.emrloop_mobile"
        }
      },
      "oauth_client": [
        {
          "client_id": "415111056854-am4j1nrqn6i812ik1dqtrpjuaumf029u.apps.googleusercontent.com",
          "client_type": 3
        }
      ],
      "api_key": [
        {
          "current_key": "AIzaSyC9bYbK9zYs5Bue9ViPYJE7u2lc9pxlD6c"
        }
      ],
      "services": {
        "appinvite_service": {
          "other_platform_oauth_client": [
            {
              "client_id": "415111056854-am4j1nrqn6i812ik1dqtrpjuaumf029u.apps.googleusercontent.com",
              "client_type": 3
            }
          ]
        }
      }
    }
  ],
  "configuration_version": "1"
}